cpmel/__init__.py
cpmel/_args_conv.py
cpmel/_mel.py
cpmel/cmds.py
cpmel/cmds.pyi
cpmel/exc.py
cpmel/object_types.py
cpmel/versions.py
cpmel/_command/__init__.py
cpmel/_command/build_new_func.py
cpmel/_command/commands.py
cpmel/_object_types/__init__.py
cpmel/_object_types/core.py
cpmel/_object_types/other.py
cpmel-3.7.0.dist-info/LICENSE
cpmel-3.7.0.dist-info/METADATA
cpmel-3.7.0.dist-info/WHEEL
cpmel-3.7.0.dist-info/top_level.txt
cpmel-3.7.0.dist-info/RECORD
